{"pageProps":{"data":{"status":true,"data":{"images":[],"longitude":-122.084,"deletedAt":null,"privacy":"public","likeCount":0,"latitude":37.4219983,"description":"Bb","title":"A","dateTime":1595631600000000,"deleted":false,"category":"Nature & Outdoor","userId":"Jrdox9oqFgbFiJZwR0F6q77GOGs2","locationName":"kkladsnfjkaadskf","commentCount":0,"user":{"gender":"","lastName":"Oluokun","followerCount":1,"userName":"sammxin","emailVerified":false,"id":"Jrdox9oqFgbFiJZwR0F6q77GOGs2","dob":"","email":"sammxin@gmail.com","description":"An About me text kjdabhkagfkafjkasnkjfhhasbfkhabdsjfabskjdbadskhfabsdabdhfjvasdf   abdhahabhjb  habhjab hjd","profileImage":"","followingCount":3,"firstName":"Samson"},"_id":"mlmeVmVOWO3iuKqVNPH3"}}},"__N_SSG":true}